drf_antd_protable/__init__.py
drf_antd_protable/filters.py
drf_antd_protable/mixins.py
drf_antd_protable/pagination.py
drf_antd_protable/version.json
drf_antd_protable/viewsets.py
drf_antd_protable/utils/__init__.py
drf_antd_protable/utils/columns.py
drf_antd_protable/utils/exporter.py
drf_antd_protable-1.0.1.dist-info/METADATA
drf_antd_protable-1.0.1.dist-info/WHEEL
drf_antd_protable-1.0.1.dist-info/top_level.txt
drf_antd_protable-1.0.1.dist-info/RECORD
